{
    "items": [
      {
        "id": 1,
        "title": "The Hobbit",
        "author": "J. R. R. Tolkien", 
        "genre": "Fantasy",
        "img": "https://m.media-amazon.com/images/I/712cDO7d73L._SL1500_.jpg",
        "price": 11.99,
        "rating": 4.64
      },
      {
        "id": 2,
        "title": "1984",
        "author": "George Orwell", 
        "genre": "Dystopian",
        "img": "https://m.media-amazon.com/images/I/612ADI+BVlL._SL1500_.jpg",
        "price": 10.22,
        "rating": 4.32
      },
      {
        "id": 3,
        "title": "Dracula",
        "author": "Bram Stoker",
        "genre": "Horror", 
        "img": "https://m.media-amazon.com/images/I/71lhU-dnJeL._SL1500_.jpg",
        "price": 10.06,
        "rating": 4.13
      },
      {
        "id": 4,
        "title": "Frankenstein",
        "author": "Mary Shelley", 
        "genre": "Horror",
        "img": "https://m.media-amazon.com/images/I/91HvX42+65L._SL1500_.jpg",
        "price": 9.99,
        "rating": 3.52
      },
      {
        "id": 5,
        "title": "Moby Dick",
        "author": "Herman Melville", 
        "genre": "Adventure",
        "img": "https://m.media-amazon.com/images/I/91xNmlf86yL._SL1500_.jpg",
        "price": 12.55,
        "rating": 4.26
      },
      {
        "id": 6,
        "title": "To Kill a Mockingbird",
        "author": "Harper Lee", 
        "genre": "Drama",
        "img": "https://m.media-amazon.com/images/I/81aY1lxk+9L._SL1500_.jpg",
        "price": 13.99,
        "rating": 4.32
      },
      {
        "id": 7,
        "title": "Fahrenheit 451",
        "author": "Ray Bradbury", 
        "genre": "Dystopian",
        "img": "https://m.media-amazon.com/images/I/61zc4fPQbIL._SL1500_.jpg",
        "price": 12.99,
        "rating": 4.07
      },
      {
        "id": 8,
        "title": "The Odyssey",
        "author": "Homer", 
        "genre": "Epic",
        "img": "https://m.media-amazon.com/images/I/81-ghHO6JyL._SL1500_.jpg",
        "price": 15.05,
        "rating": 3.78
      }
    ]
  }